tts_webui_extension/index_tts/__init__.py
tts_webui_extension/index_tts/main.py
tts_webui_extension/index_tts/ui.py
tts_webui_extension/index_tts/loader/__init__.py
tts_webui_extension/index_tts/loader/download_indextts_checkpoint.py
tts_webui_extension/index_tts/loader/get_model.py
tts_webui_extension_index_tts-0.0.2.dist-info/licenses/LICENSE
tts_webui_extension_index_tts-0.0.2.dist-info/METADATA
tts_webui_extension_index_tts-0.0.2.dist-info/WHEEL
tts_webui_extension_index_tts-0.0.2.dist-info/top_level.txt
tts_webui_extension_index_tts-0.0.2.dist-info/RECORD
